fastmath/__init__.py
fastmath/cosine_sim.py
fastmath/gaussain.py
fastmath/lib.py
fastmath/main.py
fastmath/sigmoid.py
fastmath/stats.py
fastmath/test.py
fastmath/trig.py
fastmath/calculus/__init__.py
fastmath/calculus/basic.py
fastmath-0.0.88.dist-info/LICENSE
fastmath-0.0.88.dist-info/METADATA
fastmath-0.0.88.dist-info/WHEEL
fastmath-0.0.88.dist-info/top_level.txt
fastmath-0.0.88.dist-info/RECORD
