Metadata-Version: 2.1
Name: fastmath
Version: 0.0.88
Summary: A math libary for easier use of math formulas
Home-page: https://github.com/roshanlam/FastMath
Author: Roshan Lamichhane
Author-email: roshanlamichhanenepali@gmail.com
License: UNKNOWN
Keywords: ROSHAN LAMICHHANE,ROSHAN,FAST MATH,FASTMATH
Platform: UNKNOWN
Classifier: Programming Language :: Python :: 3
Classifier: License :: OSI Approved :: MIT License
Classifier: Operating System :: OS Independent
Requires-Python: >=3.7
License-File: LICENSE
